gitflow_wotw/__init__.py
gitflow_wotw/cli_file.py
gitflow_wotw/constants.py
gitflow_wotw/actions/__init__.py
gitflow_wotw/actions/start_action.py
gitflow_wotw/arguments/__init__.py
gitflow_wotw/arguments/showcommands_argument.py
gitflow_wotw/components/__init__.py
gitflow_wotw/components/base_action.py
gitflow_wotw/components/base_argument.py
gitflow_wotw/components/base_subcommand.py
gitflow_wotw/components/command.py
gitflow_wotw/parsers/__init__.py
gitflow_wotw/parsers/parser_node.py
gitflow_wotw/parsers/parser_sink.py
gitflow_wotw/parsers/parser_source.py
gitflow_wotw/subcommands/__init__.py
gitflow_wotw/subcommands/feature_subcommand.py
gitflow_wotw/utils/__init__.py
gitflow_wotw/utils/has_descendants.py
gitflow_wotw/utils/observes_hierarchy.py
gitflow_wotw-0.2.0.dist-info/DESCRIPTION.rst
gitflow_wotw-0.2.0.dist-info/METADATA
gitflow_wotw-0.2.0.dist-info/RECORD
gitflow_wotw-0.2.0.dist-info/WHEEL
gitflow_wotw-0.2.0.dist-info/entry_points.txt
gitflow_wotw-0.2.0.dist-info/metadata.json
gitflow_wotw-0.2.0.dist-info/top_level.txt
