Metadata-Version: 2.0
Name: gitflow-wotw
Version: 0.2.0
Summary: gitflow-avh in Python via pygit2
Home-page: https://github.com/wizardsoftheweb/gitflow-wotw#readme
Author: CJ Harries
Author-email: cj@wizardsoftheweb.pro
License: ISC
Project-URL: Issue Tracker, https://github.com/wizardsoftheweb/gitflow-wotw/issues
Keywords: git,gitflow,gitflow-avh
Platform: UNKNOWN
Classifier: Development Status :: 1 - Planning
Classifier: Environment :: Console
Classifier: Topic :: Software Development :: Version Control :: Git
Requires-Dist: pygit2
Requires-Dist: pytest-runner
